cdk_organizer/__init__.py
cdk_organizer/aws/__init__.py
cdk_organizer/aws/stack.py
cdk_organizer/aws/stack_group.py
cdk_organizer/decorators/__init__.py
cdk_organizer/decorators/catch_exceptions.py
cdk_organizer/loaders/__init__.py
cdk_organizer/loaders/config_loader.py
cdk_organizer/miscellaneous/__init__.py
cdk_organizer/miscellaneous/logging.py
cdk_organizer/miscellaneous/yaml_tags/__init__.py
cdk_organizer/miscellaneous/yaml_tags/include_yaml.py
cdk_organizer/miscellaneous/yaml_tags/merge_yaml.py
cdk_organizer/stack.py
cdk_organizer/stack_group.py
cdk_organizer/terraform/__init__.py
cdk_organizer/terraform/stack.py
cdk_organizer/terraform/stack_group.py
cdk_organizer-1.11.0.dist-info/METADATA
cdk_organizer-1.11.0.dist-info/WHEEL
cdk_organizer-1.11.0.dist-info/RECORD
