Metadata-Version: 2.1
Name: cdk-organizer
Version: 1.11.0
Summary: CDK Organizer
Requires-Python: >=3.8,<3.11
Classifier: Programming Language :: Python :: 3
Classifier: Programming Language :: Python :: 3.8
Classifier: Programming Language :: Python :: 3.9
Classifier: Programming Language :: Python :: 3.10
Provides-Extra: aws
Provides-Extra: terraform
Requires-Dist: PyYAML (>=6.0,<7.0)
Requires-Dist: aws-cdk-lib (>=2.32.1,<3.0.0) ; extra == "aws"
Requires-Dist: cdktf (>=0.20.0,<0.21.0) ; extra == "terraform"
Requires-Dist: constructs (>=10.1.49,<11.0.0)
Requires-Dist: dacite (>=1.6.0,<2.0.0)
Requires-Dist: jinja2 (>=3.1.2,<4.0.0)
Requires-Dist: pyhumps (>=3.7.2,<4.0.0)
